Workbook

Sheet Ingresos
A1: Fecha | B1: Mes | C1: Fuente | D1: Descripción | E1: Valor

Sheet Gastos
A1: Fecha | B1: Mes | C1: Categoría | D1: Descripción | E1: Valor

Sheet Deudas
A1: Fecha | B1: Mes | C1: Entidad | D1: Concepto | E1: Valor

Sheet Control Cuotas
A1: Entidad | B1: Concepto | C1: Monto Total | D1: Número Cuotas | E1: Cuotas Pagadas | F1: Cuotas Restantes | G1: Valor Cuota | H1: Total Pagado | I1: Saldo Pendiente | J1: Próximo Pago | K1: Estado
F2: =D2-E2 | H2: =E2*G2 | I2: =C2-H2
F3: =D3-E3 | H3: =E3*G3 | I3: =C3-H3
F4: =D4-E4 | H4: =E4*G4 | I4: =C4-H4
F5: =D5-E5 | H5: =E5*G5 | I5: =C5-H5
F6: =D6-E6 | H6: =E6*G6 | I6: =C6-H6
F7: =D7-E7 | H7: =E7*G7 | I7: =C7-H7
F8: =D8-E8 | H8: =E8*G8 | I8: =C8-H8
F9: =D9-E9 | H9: =E9*G9 | I9: =C9-H9
F10: =D10-E10 | H10: =E10*G10 | I10: =C10-H10
F11: =D11-E11 | H11: =E11*G11 | I11: =C11-H11
F12: =D12-E12 | H12: =E12*G12 | I12: =C12-H12
F13: =D13-E13 | H13: =E13*G13 | I13: =C13-H13
... F201: =D201-E201 | H201: =E201*G201 | I201: =C201-H201

Sheet Pagos Mensuales
A1: Fecha | B1: Mes | C1: Entidad | D1: Concepto | E1: N° Cuota | F1: Valor Pagado | G1: Obs

Sheet Resumen Mensual
A1: Mes | B1: Ingresos | C1: Gastos | D1: Pago Deudas | E1: Balance Mes | F1: Balance Acumulado
A2: Enero | B2: =SUMIF(Ingresos!B:B,A2,Ingresos!E:E) | C2: =SUMIF(Gastos!B:B,A2,Gastos!E:E) | D2: =SUMIF(Deudas!B:B,A2,Deudas!E:E) | E2: =B2-C2-D2 | F2: =E2
A3: Febrero | B3: =SUMIF(Ingresos!B:B,A3,Ingresos!E:E) | C3: =SUMIF(Gastos!B:B,A3,Gastos!E:E) | D3: =SUMIF(Deudas!B:B,A3,Deudas!E:E) | E3: =B3-C3-D3 | F3: =F2+E3
A4: Marzo | B4: =SUMIF(Ingresos!B:B,A4,Ingresos!E:E) | C4: =SUMIF(Gastos!B:B,A4,Gastos!E:E) | D4: =SUMIF(Deudas!B:B,A4,Deudas!E:E) | E4: =B4-C4-D4 | F4: =F3+E4
A5: Abril | B5: =SUMIF(Ingresos!B:B,A5,Ingresos!E:E) | C5: =SUMIF(Gastos!B:B,A5,Gastos!E:E) | D5: =SUMIF(Deudas!B:B,A5,Deudas!E:E) | E5: =B5-C5-D5 | F5: =F4+E5
A6: Mayo | B6: =SUMIF(Ingresos!B:B,A6,Ingresos!E:E) | C6: =SUMIF(Gastos!B:B,A6,Gastos!E:E) | D6: =SUMIF(Deudas!B:B,A6,Deudas!E:E) | E6: =B6-C6-D6 | F6: =F5+E6
A7: Junio | B7: =SUMIF(Ingresos!B:B,A7,Ingresos!E:E) | C7: =SUMIF(Gastos!B:B,A7,Gastos!E:E) | D7: =SUMIF(Deudas!B:B,A7,Deudas!E:E) | E7: =B7-C7-D7 | F7: =F6+E7
A8: Julio | B8: =SUMIF(Ingresos!B:B,A8,Ingresos!E:E) | C8: =SUMIF(Gastos!B:B,A8,Gastos!E:E) | D8: =SUMIF(Deudas!B:B,A8,Deudas!E:E) | E8: =B8-C8-D8 | F8: =F7+E8
A9: Agosto | B9: =SUMIF(Ingresos!B:B,A9,Ingresos!E:E) | C9: =SUMIF(Gastos!B:B,A9,Gastos!E:E) | D9: =SUMIF(Deudas!B:B,A9,Deudas!E:E) | E9: =B9-C9-D9 | F9: =F8+E9
A10: Septiembre | B10: =SUMIF(Ingresos!B:B,A10,Ingresos!E:E) | C10: =SUMIF(Gastos!B:B,A10,Gastos!E:E) | D10: =SUMIF(Deudas!B:B,A10,Deudas!E:E) | E10: =B10-C10-D10 | F10: =F9+E10
A11: Octubre | B11: =SUMIF(Ingresos!B:B,A11,Ingresos!E:E) | C11: =SUMIF(Gastos!B:B,A11,Gastos!E:E) | D11: =SUMIF(Deudas!B:B,A11,Deudas!E:E) | E11: =B11-C11-D11 | F11: =F10+E11
A12: Noviembre | B12: =SUMIF(Ingresos!B:B,A12,Ingresos!E:E) | C12: =SUMIF(Gastos!B:B,A12,Gastos!E:E) | D12: =SUMIF(Deudas!B:B,A12,Deudas!E:E) | E12: =B12-C12-D12 | F12: =F11+E12
A13: Diciembre | B13: =SUMIF(Ingresos!B:B,A13,Ingresos!E:E) | C13: =SUMIF(Gastos!B:B,A13,Gastos!E:E) | D13: =SUMIF(Deudas!B:B,A13,Deudas!E:E) | E13: =B13-C13-D13 | F13: =F12+E13
