Workbook

Sheet Dashboard
A1: Indicador | B1: Valor
A2: Ingresos Totales | B2: =SUM(Ingresos!F:F) -> 13000000
A3: Gastos Totales | B3: =SUM(Gastos!E:E) -> 9433000
A4: Balance Acumulado | B4: ='Resumen Mensual'!E13 -> 3567000
A5: Deuda Pendiente | B5: =SUM('Control de Cuotas'!L:L) -> 0
A6: Cuotas Pagadas | B6: =SUM('Control de Cuotas'!I:I) -> 0
A7: Cuotas Restantes | B7: =SUM('Control de Cuotas'!J:J) -> 0

Sheet Control de Cuotas
A1: ID | B1: Entidad | C1: Concepto | D1: Monto Total | E1: Cuotas Totales | F1: Valor Cuota | G1: Fecha Inicio | H1: Día Pago | I1: Cuotas Pagadas(auto) | J1: Cuotas Restantes(auto) | K1: Total Pagado(auto) | L1: Saldo(auto) | M1: Estado
I2: =COUNTIF('Pagos de Cuotas'!C:C,A2) -> 0 | J2: =E2-I2 -> 0 | K2: =SUMIF('Pagos de Cuotas'!C:C,A2,'Pagos de Cuotas'!F:F) -> 0 | L2: =D2-K2 -> 0 | M2: =IF(L2<=0,"Finalizada",IF(I2=0,"Pendiente","En curso")) -> Finalizada
I3: =COUNTIF('Pagos de Cuotas'!C:C,A3) -> 0 | J3: =E3-I3 -> 0 | K3: =SUMIF('Pagos de Cuotas'!C:C,A3,'Pagos de Cuotas'!F:F) -> 0 | L3: =D3-K3 -> 0 | M3: =IF(L3<=0,"Finalizada",IF(I3=0,"Pendiente","En curso")) -> Finalizada
I4: =COUNTIF('Pagos de Cuotas'!C:C,A4) -> 0 | J4: =E4-I4 -> 0 | K4: =SUMIF('Pagos de Cuotas'!C:C,A4,'Pagos de Cuotas'!F:F) -> 0 | L4: =D4-K4 -> 0 | M4: =IF(L4<=0,"Finalizada",IF(I4=0,"Pendiente","En curso")) -> Finalizada
I5: =COUNTIF('Pagos de Cuotas'!C:C,A5) -> 0 | J5: =E5-I5 -> 0 | K5: =SUMIF('Pagos de Cuotas'!C:C,A5,'Pagos de Cuotas'!F:F) -> 0 | L5: =D5-K5 -> 0 | M5: =IF(L5<=0,"Finalizada",IF(I5=0,"Pendiente","En curso")) -> Finalizada
I6: =COUNTIF('Pagos de Cuotas'!C:C,A6) -> 0 | J6: =E6-I6 -> 0 | K6: =SUMIF('Pagos de Cuotas'!C:C,A6,'Pagos de Cuotas'!F:F) -> 0 | L6: =D6-K6 -> 0 | M6: =IF(L6<=0,"Finalizada",IF(I6=0,"Pendiente","En curso")) -> Finalizada
I7: =COUNTIF('Pagos de Cuotas'!C:C,A7) -> 0 | J7: =E7-I7 -> 0 | K7: =SUMIF('Pagos de Cuotas'!C:C,A7,'Pagos de Cuotas'!F:F) -> 0 | L7: =D7-K7 -> 0 | M7: =IF(L7<=0,"Finalizada",IF(I7=0,"Pendiente","En curso")) -> Finalizada
I8: =COUNTIF('Pagos de Cuotas'!C:C,A8) -> 0 | J8: =E8-I8 -> 0 | K8: =SUMIF('Pagos de Cuotas'!C:C,A8,'Pagos de Cuotas'!F:F) -> 0 | L8: =D8-K8 -> 0 | M8: =IF(L8<=0,"Finalizada",IF(I8=0,"Pendiente","En curso")) -> Finalizada
I9: =COUNTIF('Pagos de Cuotas'!C:C,A9) -> 0 | J9: =E9-I9 -> 0 | K9: =SUMIF('Pagos de Cuotas'!C:C,A9,'Pagos de Cuotas'!F:F) -> 0 | L9: =D9-K9 -> 0 | M9: =IF(L9<=0,"Finalizada",IF(I9=0,"Pendiente","En curso")) -> Finalizada
I10: =COUNTIF('Pagos de Cuotas'!C:C,A10) -> 0 | J10: =E10-I10 -> 0 | K10: =SUMIF('Pagos de Cuotas'!C:C,A10,'Pagos de Cuotas'!F:F) -> 0 | L10: =D10-K10 -> 0 | M10: =IF(L10<=0,"Finalizada",IF(I10=0,"Pendiente","En curso")) -> Finalizada
I11: =COUNTIF('Pagos de Cuotas'!C:C,A11) -> 0 | J11: =E11-I11 -> 0 | K11: =SUMIF('Pagos de Cuotas'!C:C,A11,'Pagos de Cuotas'!F:F) -> 0 | L11: =D11-K11 -> 0 | M11: =IF(L11<=0,"Finalizada",IF(I11=0,"Pendiente","En curso")) -> Finalizada
I12: =COUNTIF('Pagos de Cuotas'!C:C,A12) -> 0 | J12: =E12-I12 -> 0 | K12: =SUMIF('Pagos de Cuotas'!C:C,A12,'Pagos de Cuotas'!F:F) -> 0 | L12: =D12-K12 -> 0 | M12: =IF(L12<=0,"Finalizada",IF(I12=0,"Pendiente","En curso")) -> Finalizada
I13: =COUNTIF('Pagos de Cuotas'!C:C,A13) -> 0 | J13: =E13-I13 -> 0 | K13: =SUMIF('Pagos de Cuotas'!C:C,A13,'Pagos de Cuotas'!F:F) -> 0 | L13: =D13-K13 -> 0 | M13: =IF(L13<=0,"Finalizada",IF(I13=0,"Pendiente","En curso")) -> Finalizada
... I301: =COUNTIF('Pagos de Cuotas'!C:C,A301) -> 0 | J301: =E301-I301 -> 0 | K301: =SUMIF('Pagos de Cuotas'!C:C,A301,'Pagos de Cuotas'!F:F) -> 0 | L301: =D301-K301 -> 0 | M301: =IF(L301<=0,"Finalizada",IF(I301=0,"Pendiente","En curso")) -> Finalizada

Sheet Pagos de Cuotas
A1: Fecha | B1: Mes | C1: ID | D1: Entidad | E1: N° Cuota | F1: Valor Pagado | G1: Comprobante | H1: Observaciones

Sheet Ingresos
A1: Fecha | B1: Mes | C1: Fuente | D1: Categoría | E1: Descripción | F1: Valor
B2: Julio | C2: Shein | F2: 5000000
B3: Agosto | C3: Sueldo | F3: 1800000
B4: Agosto | C4: Talento Tech | F4: 2600000
B5: Septiembre | C5: Sueldo | F5: 1800000
B6: Octubre | C6: Sueldo | F6: 1800000

Sheet Gastos
A1: Fecha | B1: Mes | C1: Categoría | D1: Descripción | E1: Valor | F1: Necesidad/Deseo | G1: Columna1
B2: Julio | C2: Moto | E2: 2600000
B3: Julio | C3: Gilla | E3: 210000
B4: Julio | C4: Tarjetas | E4: =128000+230000 -> 358000
B5: Julio | C5: Plan | E5: 50000
B6: Agosto | C6: Eduardo | E6: 400000
B7: Agosto | C7: Titi | E7: 360000
B8: Agosto | C8: Tia Denis | E8: 300000
B9: Agosto | C9: Colonia | E9: 155000
B10: Agosto | C10: Solventa | E10: 600000
B11: Agosto | C11: Señor Jorge | E11: 600000
B12: Agosto | C12: Accesorios Moto | E12: 800000
B13: Septiembre | C13: Moto Shein | E13: =400000+800000 -> 1200000
B14: Septiembre | C14: Licencia | E14: 600000
B15: Octubre | C15: Moto Shein | E15: =400000+800000 -> 1200000

Sheet Resumen Mensual
A1: Mes | B1: Ingresos | C1: Gastos | D1: Balance Mes | E1: Balance Acumulado
A2: Enero | B2: =SUMIF(Ingresos!B:B,A2,Ingresos!F:F) -> 0 | C2: =SUMIF(Gastos!B:B,A2,Gastos!E:E) -> 0 | D2: =B2-C2 -> 0 | E2: =D2 -> 0
A3: Febrero | B3: =SUMIF(Ingresos!B:B,A3,Ingresos!F:F) -> 0 | C3: =SUMIF(Gastos!B:B,A3,Gastos!E:E) -> 0 | D3: =B3-C3 -> 0 | E3: =E2+D3 -> 0
A4: Marzo | B4: =SUMIF(Ingresos!B:B,A4,Ingresos!F:F) -> 0 | C4: =SUMIF(Gastos!B:B,A4,Gastos!E:E) -> 0 | D4: =B4-C4 -> 0 | E4: =E3+D4 -> 0
A5: Abril | B5: =SUMIF(Ingresos!B:B,A5,Ingresos!F:F) -> 0 | C5: =SUMIF(Gastos!B:B,A5,Gastos!E:E) -> 0 | D5: =B5-C5 -> 0 | E5: =E4+D5 -> 0
A6: Mayo | B6: =SUMIF(Ingresos!B:B,A6,Ingresos!F:F) -> 0 | C6: =SUMIF(Gastos!B:B,A6,Gastos!E:E) -> 0 | D6: =B6-C6 -> 0 | E6: =E5+D6 -> 0
A7: Junio | B7: =SUMIF(Ingresos!B:B,A7,Ingresos!F:F) -> 0 | C7: =SUMIF(Gastos!B:B,A7,Gastos!E:E) -> 0 | D7: =B7-C7 -> 0 | E7: =E6+D7 -> 0
A8: Julio | B8: =SUMIF(Ingresos!B:B,A8,Ingresos!F:F) -> 5000000 | C8: =SUMIF(Gastos!B:B,A8,Gastos!E:E) -> 3218000 | D8: =B8-C8 -> 1782000 | E8: =E7+D8 -> 1782000
A9: Agosto | B9: =SUMIF(Ingresos!B:B,A9,Ingresos!F:F) -> 4400000 | C9: =SUMIF(Gastos!B:B,A9,Gastos!E:E) -> 3215000 | D9: =B9-C9 -> 1185000 | E9: =E8+D9 -> 2967000
A10: Septiembre | B10: =SUMIF(Ingresos!B:B,A10,Ingresos!F:F) -> 1800000 | C10: =SUMIF(Gastos!B:B,A10,Gastos!E:E) -> 1800000 | D10: =B10-C10 -> 0 | E10: =E9+D10 -> 2967000
A11: Octubre | B11: =SUMIF(Ingresos!B:B,A11,Ingresos!F:F) -> 1800000 | C11: =SUMIF(Gastos!B:B,A11,Gastos!E:E) -> 1200000 | D11: =B11-C11 -> 600000 | E11: =E10+D11 -> 3567000
A12: Noviembre | B12: =SUMIF(Ingresos!B:B,A12,Ingresos!F:F) -> 0 | C12: =SUMIF(Gastos!B:B,A12,Gastos!E:E) -> 0 | D12: =B12-C12 -> 0 | E12: =E11+D12 -> 3567000
A13: Diciembre | B13: =SUMIF(Ingresos!B:B,A13,Ingresos!F:F) -> 0 | C13: =SUMIF(Gastos!B:B,A13,Gastos!E:E) -> 0 | D13: =B13-C13 -> 0 | E13: =E12+D13 -> 3567000
